langgraph_distributed_utils/__init__.py
langgraph_distributed_utils/constants.py
langgraph_distributed_utils/py.typed
langgraph_distributed_utils/sample_graphs.py
langgraph_distributed_utils/serde.py
langgraph_distributed_utils/conversion/__init__.py
langgraph_distributed_utils/conversion/channel.py
langgraph_distributed_utils/conversion/checkpoint.py
langgraph_distributed_utils/conversion/config.py
langgraph_distributed_utils/conversion/exception.py
langgraph_distributed_utils/conversion/graph.py
langgraph_distributed_utils/conversion/orchestrator_response.py
langgraph_distributed_utils/conversion/runopts.py
langgraph_distributed_utils/conversion/task.py
langgraph_distributed_utils/conversion/value.py
langgraph_distributed_utils/proto/__init__.py
langgraph_distributed_utils/proto/executor_pb2.py
langgraph_distributed_utils/proto/executor_pb2.pyi
langgraph_distributed_utils/proto/executor_pb2_grpc.py
langgraph_distributed_utils/proto/executor_pb2_grpc.pyi
langgraph_distributed_utils/proto/graph_pb2.py
langgraph_distributed_utils/proto/graph_pb2.pyi
langgraph_distributed_utils/proto/graph_pb2_grpc.py
langgraph_distributed_utils/proto/graph_pb2_grpc.pyi
langgraph_distributed_utils/proto/runtime_pb2.py
langgraph_distributed_utils/proto/runtime_pb2.pyi
langgraph_distributed_utils/proto/runtime_pb2_grpc.py
langgraph_distributed_utils/proto/runtime_pb2_grpc.pyi
langgraph_distributed_utils/proto/types_pb2.py
langgraph_distributed_utils/proto/types_pb2.pyi
langgraph_distributed_utils/proto/types_pb2_grpc.py
langgraph_distributed_utils/proto/types_pb2_grpc.pyi
langgraph_distributed_utils/runtime_client/patch.py
langgraph_distributed_utils-0.0.1a3.dist-info/METADATA
langgraph_distributed_utils-0.0.1a3.dist-info/WHEEL
langgraph_distributed_utils-0.0.1a3.dist-info/RECORD
