Metadata-Version: 2.4
Name: langgraph-distributed-utils
Version: 0.0.1a3
Summary: LangGraph Distributed Runtime utilities shared by langgraph-executor and langgraph-runtime-integration.
Requires-Python: >=3.11
Requires-Dist: grpcio>=1.73.1
Requires-Dist: langgraph>=0.6.5
Requires-Dist: protobuf>=4.25.0
